autovul/__init__.py
autovul/version.py
autovul-1.0.9.dist-info/LICENSE
autovul-1.0.9.dist-info/METADATA
autovul-1.0.9.dist-info/WHEEL
autovul-1.0.9.dist-info/top_level.txt
autovul-1.0.9.dist-info/RECORD
