Metadata-Version: 2.1
Name: autovul
Version: 1.0.9
Summary: minimum code implementation for our USENIX paper `On the Security Risks of AutoML`.
Home-page: UNKNOWN
Author: Ren Pang
Author-email: rbp5354@psu.edu
License: GPL-3
Keywords: pytorch,image classification,automl
Platform: UNKNOWN
Classifier: Environment :: GPU :: NVIDIA CUDA :: 11.1
Classifier: Intended Audience :: Developers
Classifier: Intended Audience :: Education
Classifier: Intended Audience :: Science/Research
Classifier: License :: OSI Approved :: GNU General Public License v3 (GPLv3)
Classifier: Topic :: Scientific/Engineering :: Artificial Intelligence
Classifier: Topic :: Scientific/Engineering :: Image Recognition
Classifier: Topic :: Software Development :: Libraries :: Python Modules
Classifier: Programming Language :: Python :: 3.9
Requires-Python: >=3.9.6
License-File: LICENSE
Requires-Dist: torch (>=1.10.0)
Requires-Dist: torchvision (>=0.11.1)
Requires-Dist: numpy (>=1.20.3)
Requires-Dist: matplotlib (>=3.4.2)
Requires-Dist: pyyaml (>=5.3.1)
Requires-Dist: tqdm (>=4.54.1)
Requires-Dist: adversarial-robustness-toolbox
